innocuous_api/__init__.py
innocuous_api/api.py
innocuous_api-1.1.3.post2.dist-info/METADATA
innocuous_api-1.1.3.post2.dist-info/WHEEL
innocuous_api-1.1.3.post2.dist-info/top_level.txt
innocuous_api-1.1.3.post2.dist-info/RECORD
