Metadata-Version: 2.1
Name: innocuous-api
Version: 1.1.3.post2
Summary: Innocuous Book API
Home-page: 
Author: noam
Author-email: noamsrosenberg@gmail.com
License: UNKNOWN
Keywords: innocuousbook
Platform: UNKNOWN
Requires-Dist: colorlog
Requires-Dist: halo
Requires-Dist: pyjwt
Requires-Dist: requests
Requires-Dist: pyyaml
